{
  "name": "install",
  "short_description": "Install board",
  "full_help": "install\n\nDescription: \nInstall board\n\nSyntax: \ninstall  [-quiet] [-verbose] <board>\n\nReturns: \nNothing\n\nUsage: \n  Name        Description\n  -----------------------\n  [-quiet]    Ignore command errors\n  [-verbose]  Suspend message limits during command execution\n  <board>     Name of board to install\n\nCategories: \nTools\n",
  "custom_snippet": null,
  "arguments": [
    {
      "flag": "-quiet",
      "description": "Ignore command errors"
    },
    {
      "flag": "-verbose",
      "description": "Suspend message limits during command execution"
    }
  ]
}